{"chunk_definitions":[{"row":9,"row_count":1,"visible":true,"expansion_state":0,"options":{"engine":"r","label":"setup","include":false},"document_id":"35B3DE1F","chunk_id":"csetup_chunk","chunk_label":"setup"},{"row":29,"row_count":1,"visible":true,"expansion_state":0,"options":{"engine":"r","eval":true,"echo":true,"label":"unnamed-chunk-68"},"document_id":"35B3DE1F","chunk_id":"cq7pfj8mku97j","chunk_label":"unnamed-chunk-1"},{"row":51,"row_count":1,"visible":true,"expansion_state":0,"options":{"engine":"r","eval":true,"echo":true,"label":"unnamed-chunk-73"},"document_id":"35B3DE1F","chunk_id":"cf6en0c424rfy","chunk_label":"unnamed-chunk-2"},{"row":75,"row_count":1,"visible":true,"expansion_state":0,"options":{"engine":"r","eval":true,"echo":true,"label":"unnamed-chunk-64"},"document_id":"35B3DE1F","chunk_id":"cy84cb5s2juu7","chunk_label":"unnamed-chunk-3"},{"row":96,"row_count":1,"visible":true,"expansion_state":0,"options":{"engine":"r","eval":true,"echo":true,"label":"unnamed-chunk-32"},"document_id":"35B3DE1F","chunk_id":"c5fh3s3fkqhz8","chunk_label":"unnamed-chunk-4"},{"row":115,"row_count":1,"visible":true,"expansion_state":0,"options":{"engine":"r","eval":true,"echo":true,"label":"unnamed-chunk-63"},"document_id":"35B3DE1F","chunk_id":"cjbmfs8r0efe9","chunk_label":"unnamed-chunk-5"},{"row":159,"row_count":1,"visible":true,"expansion_state":0,"options":{"engine":"r","eval":true,"echo":true,"label":"unnamed-chunk-4"},"document_id":"35B3DE1F","chunk_id":"cvmm8fbcjayby","chunk_label":"unnamed-chunk-6"}],"doc_write_time":1694607022,"working_dir":null,"default_chunk_options":{"echo":true}}